form_api/__init__.py
form_api/api_client.py
form_api/configuration.py
form_api/rest.py
form_api/api/__init__.py
form_api/api/client.py
form_api/api/pdf_api.py
form_api/models/__init__.py
form_api/models/authentication_error.py
form_api/models/authentication_success_response.py
form_api/models/combine_pdfs_data.py
form_api/models/combined_submission.py
form_api/models/combined_submission_action.py
form_api/models/combined_submission_data.py
form_api/models/create_combined_submission_response.py
form_api/models/create_custom_file_data.py
form_api/models/create_custom_file_response.py
form_api/models/create_folder_data.py
form_api/models/create_submission_batch_response.py
form_api/models/create_submission_batch_submissions_response.py
form_api/models/create_submission_data_request_data.py
form_api/models/create_submission_data_request_token_response.py
form_api/models/create_submission_data_request_token_response_token.py
form_api/models/create_submission_response.py
form_api/models/create_template_data.py
form_api/models/custom_file.py
form_api/models/error.py
form_api/models/folder.py
form_api/models/folders_folder.py
form_api/models/invalid_request.py
form_api/models/move_folder_data.py
form_api/models/move_template_data.py
form_api/models/pending_template.py
form_api/models/rename_folder_data.py
form_api/models/submission.py
form_api/models/submission_action.py
form_api/models/submission_batch.py
form_api/models/submission_batch_data.py
form_api/models/submission_data.py
form_api/models/submission_data_batch_request.py
form_api/models/submission_data_request.py
form_api/models/template.py
form_api/models/templatesv2_template.py
form_api/models/templatesv2_template_document.py
form_api/models/templatesv2_template_document_metadata.py
form_api/models/update_data_request_response.py
form_api/models/update_submission_data_request_data.py
test/__init__.py
test/test_authentication_error.py
test/test_authentication_success_response.py
test/test_client_integration.py
form_api-1.12.0.dist-info/LICENSE
form_api-1.12.0.dist-info/METADATA
form_api-1.12.0.dist-info/WHEEL
form_api-1.12.0.dist-info/top_level.txt
form_api-1.12.0.dist-info/RECORD
